{
  "alerted_fingerprints": [
    "3507cdb0d7128d2f",
    "9e3a92468fe2968f",
    "c8426fa0b054ad9b",
    "e25a84e0ec121234",
    "ec8bedf63c803033",
    "fdd1d854ba17240a"
  ],
  "last_added_fingerprints": [
    "e25a84e0ec121234"
  ],
  "last_alert_count": 1,
  "last_line": "Fundstrat daytime watch: 1 new urgent/action-changing alert(s).",
  "policy": "Push only when a compact full-body-derived Fundstrat item changes act, wait, re-check, research, trim, hedge, or size posture. Fluff/context updates stay quiet.",
  "schema_version": 1,
  "updated_at": "2026-06-12T12:48:27.888360-04:00"
}
