{
  "prior_snapshot_date": "2026-06-25",
  "current_snapshot_date": "2026-06-25",
  "changes": [
    {
      "ticker": "AVGO",
      "account": "Individual ...254 Individual ...254",
      "owner": "SKB",
      "broker": "Schwab",
      "action": "VALUE_CHANGE",
      "shares_before": 18.0,
      "shares_after": 18.0,
      "share_delta": 0.0,
      "market_value_before": 6842.34,
      "market_value_after": 6839.28,
      "market_value_delta": -3.06,
      "tracked": false
    },
    {
      "ticker": "BMNR",
      "account": "Individual ...254 Individual ...254",
      "owner": "SKB",
      "broker": "Schwab",
      "action": "VALUE_CHANGE",
      "shares_before": 73.0,
      "shares_after": 73.0,
      "share_delta": 0.0,
      "market_value_before": 974.55,
      "market_value_after": 976.01,
      "market_value_delta": 1.46,
      "tracked": true
    },
    {
      "ticker": "CCJ",
      "account": "Individual ...254 Individual ...254",
      "owner": "SKB",
      "broker": "Schwab",
      "action": "VALUE_CHANGE",
      "shares_before": 40.0,
      "shares_after": 40.0,
      "share_delta": 0.0,
      "market_value_before": 4143.2,
      "market_value_after": 4110.0,
      "market_value_delta": -33.2,
      "tracked": false
    },
    {
      "ticker": "DRIV",
      "account": "Individual ...254 Individual ...254",
      "owner": "SKB",
      "broker": "Schwab",
      "action": "VALUE_CHANGE",
      "shares_before": 130.0,
      "shares_after": 130.0,
      "share_delta": 0.0,
      "market_value_before": 4937.4,
      "market_value_after": 4950.4,
      "market_value_delta": 13.0,
      "tracked": false
    },
    {
      "ticker": "FN",
      "account": "Individual ...254 Individual ...254",
      "owner": "SKB",
      "broker": "Schwab",
      "action": "VALUE_CHANGE",
      "shares_before": 5.0,
      "shares_after": 5.0,
      "share_delta": 0.0,
      "market_value_before": 2838.95,
      "market_value_after": 2830.0,
      "market_value_delta": -8.95,
      "tracked": false
    },
    {
      "ticker": "GDX",
      "account": "Individual ...254 Individual ...254",
      "owner": "SKB",
      "broker": "Schwab",
      "action": "VALUE_CHANGE",
      "shares_before": 100.0,
      "shares_after": 100.0,
      "share_delta": 0.0,
      "market_value_before": 7567.0,
      "market_value_after": 7575.0,
      "market_value_delta": 8.0,
      "tracked": false
    },
    {
      "ticker": "GDX",
      "account": "PCRA Trust ...651 PCRA Trust ...651",
      "owner": "Parents",
      "broker": "Schwab",
      "action": "VALUE_CHANGE",
      "shares_before": 151.0,
      "shares_after": 151.0,
      "share_delta": 0.0,
      "market_value_before": 11426.17,
      "market_value_after": 11438.25,
      "market_value_delta": 12.08,
      "tracked": false
    },
    {
      "ticker": "GOOGL",
      "account": "Individual ...254 Individual ...254",
      "owner": "SKB",
      "broker": "Schwab",
      "action": "VALUE_CHANGE",
      "shares_before": 55.0,
      "shares_after": 55.0,
      "share_delta": 0.0,
      "market_value_before": 18814.95,
      "market_value_after": 18888.1,
      "market_value_delta": 73.15,
      "tracked": false
    },
    {
      "ticker": "GRNJ",
      "account": "Individual ...254 Individual ...254",
      "owner": "SKB",
      "broker": "Schwab",
      "action": "VALUE_CHANGE",
      "shares_before": 739.0,
      "shares_after": 739.0,
      "share_delta": 0.0,
      "market_value_before": 22916.39,
      "market_value_after": 22827.71,
      "market_value_delta": -88.68,
      "tracked": true
    },
    {
      "ticker": "GRNJ",
      "account": "PCRA Trust ...651 PCRA Trust ...651",
      "owner": "Parents",
      "broker": "Schwab",
      "action": "VALUE_CHANGE",
      "shares_before": 1628.0,
      "shares_after": 1628.0,
      "share_delta": 0.0,
      "market_value_before": 50484.28,
      "market_value_after": 50288.92,
      "market_value_delta": -195.36,
      "tracked": true
    },
    {
      "ticker": "GRNY",
      "account": "Individual ...254 Individual ...254",
      "owner": "SKB",
      "broker": "Schwab",
      "action": "VALUE_CHANGE",
      "shares_before": 400.0,
      "shares_after": 400.0,
      "share_delta": 0.0,
      "market_value_before": 10788.0,
      "market_value_after": 10751.2,
      "market_value_delta": -36.8,
      "tracked": true
    },
    {
      "ticker": "GRNY",
      "account": "PCRA Trust ...651 PCRA Trust ...651",
      "owner": "Parents",
      "broker": "Schwab",
      "action": "VALUE_CHANGE",
      "shares_before": 2700.0,
      "shares_after": 2700.0,
      "share_delta": 0.0,
      "market_value_before": 72819.0,
      "market_value_after": 72570.6,
      "market_value_delta": -248.4,
      "tracked": true
    },
    {
      "ticker": "HYPE",
      "account": "Robinhood Crypto 8794",
      "owner": "SKB",
      "broker": "Robinhood",
      "action": "VALUE_CHANGE",
      "shares_before": 18.0197,
      "shares_after": 18.0197,
      "share_delta": 0.0,
      "market_value_before": 1150.1,
      "market_value_after": 1137.69,
      "market_value_delta": -12.41,
      "tracked": false
    },
    {
      "ticker": "ITA",
      "account": "PCRA Trust ...651 PCRA Trust ...651",
      "owner": "Parents",
      "broker": "Schwab",
      "action": "VALUE_CHANGE",
      "shares_before": 51.0,
      "shares_after": 51.0,
      "share_delta": 0.0,
      "market_value_before": 12106.38,
      "market_value_after": 12051.3,
      "market_value_delta": -55.08,
      "tracked": false
    },
    {
      "ticker": "IVES",
      "account": "PCRA Trust ...651 PCRA Trust ...651",
      "owner": "Parents",
      "broker": "Schwab",
      "action": "VALUE_CHANGE",
      "shares_before": 693.0,
      "shares_after": 693.0,
      "share_delta": 0.0,
      "market_value_before": 24864.84,
      "market_value_after": 24788.61,
      "market_value_delta": -76.23,
      "tracked": true
    },
    {
      "ticker": "JPM",
      "account": "Individual ...254 Individual ...254",
      "owner": "SKB",
      "broker": "Schwab",
      "action": "VALUE_CHANGE",
      "shares_before": 18.0,
      "shares_after": 18.0,
      "share_delta": 0.0,
      "market_value_before": 6032.16,
      "market_value_after": 6067.62,
      "market_value_delta": 35.46,
      "tracked": false
    },
    {
      "ticker": "LIT",
      "account": "PCRA Trust ...651 PCRA Trust ...651",
      "owner": "Parents",
      "broker": "Schwab",
      "action": "VALUE_CHANGE",
      "shares_before": 20.0,
      "shares_after": 20.0,
      "share_delta": 0.0,
      "market_value_before": 1569.0,
      "market_value_after": 1576.0,
      "market_value_delta": 7.0,
      "tracked": false
    },
    {
      "ticker": "MRVL",
      "account": "Individual ...254 Individual ...254",
      "owner": "SKB",
      "broker": "Schwab",
      "action": "VALUE_CHANGE",
      "shares_before": 15.0,
      "shares_after": 15.0,
      "share_delta": 0.0,
      "market_value_before": 4260.0,
      "market_value_after": 4209.15,
      "market_value_delta": -50.85,
      "tracked": false
    },
    {
      "ticker": "MSFT",
      "account": "Individual ...254 Individual ...254",
      "owner": "SKB",
      "broker": "Schwab",
      "action": "VALUE_CHANGE",
      "shares_before": 2.0,
      "shares_after": 2.0,
      "share_delta": 0.0,
      "market_value_before": 705.66,
      "market_value_after": 708.14,
      "market_value_delta": 2.48,
      "tracked": false
    },
    {
      "ticker": "NVDA",
      "account": "Individual ...254 Individual ...254",
      "owner": "SKB",
      "broker": "Schwab",
      "action": "VALUE_CHANGE",
      "shares_before": 17.0,
      "shares_after": 17.0,
      "share_delta": 0.0,
      "market_value_before": 3334.04,
      "market_value_after": 3315.85,
      "market_value_delta": -18.19,
      "tracked": true
    },
    {
      "ticker": "RPG",
      "account": "PCRA Trust ...651 PCRA Trust ...651",
      "owner": "Parents",
      "broker": "Schwab",
      "action": "VALUE_CHANGE",
      "shares_before": 196.0,
      "shares_after": 196.0,
      "share_delta": 0.0,
      "market_value_before": 12348.0,
      "market_value_after": 12338.2,
      "market_value_delta": -9.8,
      "tracked": false
    },
    {
      "ticker": "SIL",
      "account": "PCRA Trust ...651 PCRA Trust ...651",
      "owner": "Parents",
      "broker": "Schwab",
      "action": "VALUE_CHANGE",
      "shares_before": 68.0,
      "shares_after": 68.0,
      "share_delta": 0.0,
      "market_value_before": 5242.12,
      "market_value_after": 5304.0,
      "market_value_delta": 61.88,
      "tracked": false
    },
    {
      "ticker": "SMH",
      "account": "Individual ...254 Individual ...254",
      "owner": "SKB",
      "broker": "Schwab",
      "action": "VALUE_CHANGE",
      "shares_before": 21.0,
      "shares_after": 21.0,
      "share_delta": 0.0,
      "market_value_before": 13395.9,
      "market_value_after": 13324.5,
      "market_value_delta": -71.4,
      "tracked": true
    },
    {
      "ticker": "SMH",
      "account": "PCRA Trust ...651 PCRA Trust ...651",
      "owner": "Parents",
      "broker": "Schwab",
      "action": "VALUE_CHANGE",
      "shares_before": 75.0,
      "shares_after": 75.0,
      "share_delta": 0.0,
      "market_value_before": 47842.5,
      "market_value_after": 47604.75,
      "market_value_delta": -237.75,
      "tracked": true
    },
    {
      "ticker": "SOXX",
      "account": "PCRA Trust ...651 PCRA Trust ...651",
      "owner": "Parents",
      "broker": "Schwab",
      "action": "VALUE_CHANGE",
      "shares_before": 9.0,
      "shares_after": 9.0,
      "share_delta": 0.0,
      "market_value_before": 5644.08,
      "market_value_after": 5612.28,
      "market_value_delta": -31.8,
      "tracked": false
    },
    {
      "ticker": "VRT",
      "account": "Individual ...254 Individual ...254",
      "owner": "SKB",
      "broker": "Schwab",
      "action": "VALUE_CHANGE",
      "shares_before": 36.0,
      "shares_after": 36.0,
      "share_delta": 0.0,
      "market_value_before": 11720.52,
      "market_value_after": 11700.0,
      "market_value_delta": -20.52,
      "tracked": false
    },
    {
      "ticker": "XLF",
      "account": "PCRA Trust ...651 PCRA Trust ...651",
      "owner": "Parents",
      "broker": "Schwab",
      "action": "VALUE_CHANGE",
      "shares_before": 913.0,
      "shares_after": 913.0,
      "share_delta": 0.0,
      "market_value_before": 48882.02,
      "market_value_after": 48977.89,
      "market_value_delta": 95.87,
      "tracked": true
    },
    {
      "ticker": "XLRE",
      "account": "PCRA Trust ...651 PCRA Trust ...651",
      "owner": "Parents",
      "broker": "Schwab",
      "action": "VALUE_CHANGE",
      "shares_before": 293.4046,
      "shares_after": 293.4046,
      "share_delta": 0.0,
      "market_value_before": 13082.91,
      "market_value_after": 13121.05,
      "market_value_delta": 38.14,
      "tracked": false
    },
    {
      "ticker": "XLU",
      "account": "PCRA Trust ...651 PCRA Trust ...651",
      "owner": "Parents",
      "broker": "Schwab",
      "action": "VALUE_CHANGE",
      "shares_before": 491.8893,
      "shares_after": 491.8893,
      "share_delta": 0.0,
      "market_value_before": 22553.12,
      "market_value_after": 22577.72,
      "market_value_delta": 24.6,
      "tracked": false
    }
  ],
  "counts": {
    "VALUE_CHANGE": 29
  }
}
